[
  {
    "id": 1,
    "name": "Megamind",
    "url": "http://commondatastorage.googleapis.com/gtv-videos-bucket/sample/BigBuckBunny.mp4"
  },
  {
    "id": 2,
    "name": "Everyone is Fine",
    "url": "http://techslides.com/demos/sample-videos/small.mp4"
  },
  {
    "id": 3,
    "name": "Turbo",
    "url": "http://commondatastorage.googleapis.com/gtv-videos-bucket/sample/BigBuckBunny.mp4"
  },
  {
    "id": 4,
    "name": "Sonic 2",
    "url": "http://commondatastorage.googleapis.com/gtv-videos-bucket/sample/BigBuckBunny.mp4"
  }
]
